<?xml version="1.0" encoding="UTF-8" ?>
<Environment >
<!--Time out-->
    <TimeOut>5</TimeOut>
    <!--General-->
    <!-- <PlatformName>web</PlatformName> -->
     <!-- WEb -->
      <ImageRepo>C:\\Automation\\FinalProject01\\ImageRepository\\</ImageRepo>
    <BrowserName>chrome</BrowserName>
    <Url>https://parabank.parasoft.com/parabank/index.htm</Url>
    <!--Mobile-->
    <UDID>4200b66deef31421</UDID>
    <AppPackage>com.experitest.ExperiBank</AppPackage>
    <AppActivity>.LoginActivity</AppActivity>
    <AppiumServer>http://localhost:4723/wd/hub</AppiumServer>
    <!--API-->
    <urlAPI>http://localhost:9000/</urlAPI>
    <!--Electron-->
    <ElectronDriverPath>./Drivers/electrondriver.exe</ElectronDriverPath>
    <ElectronAppPath>C:/Automation/electron-api-demos-windows/Electron API Demos-win32-ia32/Electron API Demos.exe</ElectronAppPath>
    <!--Desktop-->
    <CalculatorApp>Microsoft.WindowsCalculator_8wekyb3d8bbwe!App</CalculatorApp>
    <AppiumServerDesktop>http://127.0.0.1:4723</AppiumServerDesktop>
    <!--Database-->
    <DBURL>jdbc:mysql://remotemysql.com:3306/uYwDViIyKr</DBURL>
    <DBUserName>uYwDViIyKr</DBUserName>
    <DBPassword>zP6Vc600wm</DBPassword>
    <!--Data Driven Testing-->
    <DDTFile>./DDTFiles/users.csv</DDTFile>
</Environment>